smoothlogging/__init__.py
smoothlogging/version.py
smoothlogging-0.1.154.dist-info/METADATA
smoothlogging-0.1.154.dist-info/RECORD
smoothlogging-0.1.154.dist-info/WHEEL
smoothlogging-0.1.154.dist-info/top_level.txt
