Metadata-Version: 2.1
Name: smoothlogging
Version: 0.1.154
Summary: smoothlogging helps to log easily to file with timestamp + standard output
Home-page: https://github.com/blasebast/smoothlogging
Author: Sebastian Blasiak
Author-email: sebastian.blasiak@gmail.com
License: GNU General Public License v3
Keywords: sebastian,blasiak,logging,smoothlogging,logfile
Platform: UNKNOWN
Classifier: Development Status :: 2 - Pre-Alpha
Classifier: Intended Audience :: Developers
Classifier: License :: OSI Approved :: GNU General Public License v3 (GPLv3)
Classifier: Natural Language :: English
Classifier: Programming Language :: Python :: 2
Classifier: Programming Language :: Python :: 2.6
Classifier: Programming Language :: Python :: 2.7
Classifier: Programming Language :: Python :: 3
Classifier: Programming Language :: Python :: 3.3
Classifier: Programming Language :: Python :: 3.4
Classifier: Programming Language :: Python :: 3.5
